backbone_network/__init__.py
backbone_network/backbone.py
backbone_network-1.1.3.dist-info/LICENSE.txt
backbone_network-1.1.3.dist-info/METADATA
backbone_network-1.1.3.dist-info/WHEEL
backbone_network-1.1.3.dist-info/top_level.txt
backbone_network-1.1.3.dist-info/RECORD
